MANIFEST.in
README.txt
setup.py
docs/HISTORY.txt
docs/INSTALL.txt
docs/LICENSE.GPL
docs/LICENSE.txt
wildcard/__init__.py
wildcard/__init__.pyc
wildcard.readonly.egg-info/PKG-INFO
wildcard.readonly.egg-info/SOURCES.txt
wildcard.readonly.egg-info/dependency_links.txt
wildcard.readonly.egg-info/namespace_packages.txt
wildcard.readonly.egg-info/not-zip-safe
wildcard.readonly.egg-info/requires.txt
wildcard.readonly.egg-info/top_level.txt
wildcard/readonly/__init__.py
wildcard/readonly/__init__.pyc
wildcard/readonly/configure.zcml
wildcard/readonly/mail.py
wildcard/readonly/mail.pyc
wildcard/readonly/mail.zcml
wildcard/readonly/readonly-conditional.zcml
wildcard/readonly/readonly-doom.zcml
wildcard/readonly/readonly.zcml
wildcard/readonly/tests.py