Metadata-Version: 1.1
Name: wildcard.readonly
Version: 1.0
Summary: Easily setup readonly zeo clients
Home-page: https://github.com/collective/wildcard.readonly
Author: Nathan Van Gheem
Author-email: vangheem@gmail.com
License: GPL
Platform: UNKNOWN
Classifier: Framework :: Plone
Classifier: Programming Language :: Python
Classifier: Framework :: Plone
Classifier: Framework :: Plone :: 4.0
Classifier: Framework :: Plone :: 4.1
Classifier: Framework :: Plone :: 4.2
Classifier: Framework :: Plone :: 4.3
